ib_dl/__init__.py
ib_dl/_version.py
ib_dl/download.py
ib_dl-1.5.3.dist-info/LICENSE
ib_dl-1.5.3.dist-info/METADATA
ib_dl-1.5.3.dist-info/WHEEL
ib_dl-1.5.3.dist-info/entry_points.txt
ib_dl-1.5.3.dist-info/top_level.txt
ib_dl-1.5.3.dist-info/RECORD
