Metadata-Version: 2.1
Name: ib-dl
Version: 1.5.3
Summary: Historical market data downloader using Interactive Brokers TWS
Home-page: https://github.com/tibkiss/ib_dl
Author: Tibor Kiss
Author-email: tibor.kiss@gmail.com
License: Apache License, Version 2.0
Platform: UNKNOWN
Classifier: Development Status :: 4 - Beta
Classifier: License :: OSI Approved :: Apache Software License
Classifier: Programming Language :: Python :: 3.6
Classifier: Topic :: Office/Business :: Financial :: Investment
Requires-Python: >=3.6
Requires-Dist: click (==6.7)
Requires-Dist: ib-insync (==0.8.15)
Requires-Dist: pandas (==0.21.1)
